MANIFEST.in
README
setup.cfg
setup.py
data/buildings.dbf
data/buildings.keywords
data/buildings.prj
data/buildings.shp
data/buildings.shx
data/buildings_poly.dbf
data/buildings_poly.keywords
data/buildings_poly.prj
data/buildings_poly.shp
data/buildings_poly.shx
data/buildings_poly_centroids.dbf
data/buildings_poly_centroids.keywords
data/buildings_poly_centroids.prj
data/buildings_poly_centroids.shp
data/buildings_poly_centroids.shx
data/earthquake.keywords
data/earthquake.tif
data/grid_without_projection.asc
data/highway.dbf
data/highway.keywords
data/highway.prj
data/highway.shp
data/highway.shx
data/highway.sld
data/schools.dbf
data/schools.keywords
data/schools.prj
data/schools.shp
data/schools.shx
data/test_grid.asc
data/test_grid.prj
data/test_polygon.dbf
data/test_polygon.prj
data/test_polygon.shp
data/test_polygon.shx
data/tsunami_exposure.dbf
data/tsunami_exposure.keywords
data/tsunami_exposure.prj
data/tsunami_exposure.shp
data/tsunami_exposure.shx
python_safe.egg-info/PKG-INFO
python_safe.egg-info/SOURCES.txt
python_safe.egg-info/dependency_links.txt
python_safe.egg-info/top_level.txt
safe/__init__.py
safe/engine/__init__.py
safe/engine/interpolation.py
safe/engine/interpolation2d.py
safe/engine/numerics.py
safe/engine/polygon.py
safe/impact_functions/__init__.py
safe/storage/__init__.py
safe/storage/core.py
safe/storage/projection.py
safe/storage/raster.py
safe/storage/test_io.py
safe/storage/utilities.py
safe/storage/utilities_test.py
safe/storage/vector.py