Metadata-Version: 1.0
Name: python-safe
Version: 0.1.7
Summary: Spatial Analysis F* Engine
Home-page: http://github.com/AIFDR/python-safe
Author: Ariel Núñez
Author-email: ingenieroariel@gmail.com
License: BSD
Keywords: gis vector feature raster data
Platform: UNKNOWN
Classifier: Development Status :: 2 - Pre-Alpha
Classifier: Intended Audience :: Developers
Classifier: Intended Audience :: Science/Research
Classifier: License :: OSI Approved :: BSD License
Classifier: Operating System :: OS Independent
Classifier: Programming Language :: Python
Classifier: Topic :: Scientific/Engineering :: GIS
